pyclad/__init__.py
pyclad/analysis/__init__.py
pyclad/analysis/scenario_heatmap.py
pyclad/callbacks/__init__.py
pyclad/callbacks/callback.py
pyclad/callbacks/composite_callback.py
pyclad/callbacks/evaluation/__init__.py
pyclad/callbacks/evaluation/concept_metric_evaluation.py
pyclad/callbacks/evaluation/energy_evaluation.py
pyclad/callbacks/evaluation/memory_usage.py
pyclad/callbacks/evaluation/time_evaluation.py
pyclad/data/__init__.py
pyclad/data/concept.py
pyclad/data/dataset.py
pyclad/data/datasets/__init__.py
pyclad/data/datasets/concepts_dataset.py
pyclad/data/datasets/energy_plants_dataset.py
pyclad/data/datasets/nsl_kdd_dataset.py
pyclad/data/datasets/unsw_dataset.py
pyclad/data/datasets/wind_energy_dataset.py
pyclad/data/readers/__init__.py
pyclad/data/readers/concepts_readers.py
pyclad/metrics/__init__.py
pyclad/metrics/base/__init__.py
pyclad/metrics/base/base_metric.py
pyclad/metrics/base/roc_auc.py
pyclad/metrics/continual/__init__.py
pyclad/metrics/continual/average_continual.py
pyclad/metrics/continual/backward_transfer.py
pyclad/metrics/continual/concepts_metric.py
pyclad/metrics/continual/forward_transfer.py
pyclad/models/__init__.py
pyclad/models/model.py
pyclad/models/adapters/__init__.py
pyclad/models/adapters/pyod_adapters.py
pyclad/models/autoencoder/__init__.py
pyclad/models/autoencoder/autoencoder.py
pyclad/models/autoencoder/builder.py
pyclad/models/autoencoder/config.py
pyclad/models/autoencoder/loss.py
pyclad/models/autoencoder/standard/__init__.py
pyclad/models/autoencoder/standard/gru.py
pyclad/models/autoencoder/standard/lstm.py
pyclad/models/autoencoder/standard/tcn.py
pyclad/models/autoencoder/variational/__init__.py
pyclad/models/autoencoder/variational/gru.py
pyclad/models/autoencoder/variational/lstm.py
pyclad/models/autoencoder/variational/tcn.py
pyclad/output/__init__.py
pyclad/output/json_writer.py
pyclad/output/output_writer.py
pyclad/scenarios/__init__.py
pyclad/scenarios/concept_agnostic.py
pyclad/scenarios/concept_aware.py
pyclad-0.3.0.dist-info/METADATA
pyclad-0.3.0.dist-info/WHEEL
pyclad-0.3.0.dist-info/licenses/LICENSE
pyclad-0.3.0.dist-info/RECORD
